backloader/__init__.py
backloader-1.0.0.dist-info/METADATA
backloader-1.0.0.dist-info/WHEEL
backloader-1.0.0.dist-info/top_level.txt
backloader-1.0.0.dist-info/RECORD
